lc7001/aio.py
lc7001-1.0.5.dist-info/LICENSE
lc7001-1.0.5.dist-info/METADATA
lc7001-1.0.5.dist-info/WHEEL
lc7001-1.0.5.dist-info/top_level.txt
lc7001-1.0.5.dist-info/RECORD
