Metadata-Version: 2.1
Name: lc7001
Version: 1.0.5
Summary: Legrand LC7001 interface
Home-page: https://github.com/rtyle/lc7001
Author: Ross Tyler
Author-email: 
License: UNKNOWN
Project-URL: Bug Tracker, https://github.com/rtyle/lc7001/issues
Platform: UNKNOWN
Classifier: Programming Language :: Python :: 3
Classifier: License :: OSI Approved :: MIT License
Classifier: Operating System :: OS Independent
Requires-Python: >=3.8
License-File: LICENSE
